{
    "chunk_id": 599997604793,
    "source_file": "Mother_of_Flamlings_Spirit.md",
    "img_url": "https://oyster.ignimgs.com/mediawiki/apis.ign.com/black-myth-wukong/4/42/Mother_of_Flamlings_Location.jpg",
    "alt_text": "Mother of Flamlings Location.jpg",
    "position_desc": 2,
    "summary_promot": "You are given an image and related metadata and context.\n\n            Metadata:\n            - Document Title: Mother of Flamlings Spirit\n            - Section Title: Mother of Flamlings Location\n\n            Context:\n            - Preceding Text: \"# Mother of Flamlings Spirit\n\n## Mother of Flamlings Location\n\nOnce you've completed the Iron Ball challenge in the Flaming Mountains and unlocked the Fallen Furnace Crater Keeper's Shrine, head back down the hill and take the newly opened passage on the left. Follow the path until you find a pile of glowing rocks lying in a large clearing. Approach the rocks to awaken the Flint Vanguard.\n\nContinue down the path after you've defeated the Flint Vanguard, and look to the left to find a small, glowing spot in the ground. Interact with the glowing spot and deliver **four Flame Ores** to summon the Mother of Flamlings.\"\n            - Following Text: \"You can get Flame Ores by defeating Flamlings.\"\n\n            Your task:\n            1. Generate a **short, clear, and informative English summary** of the image.\n            2. Focus primarily on the **preceding and following text** to infer the image's **purpose, content, or narrative role**.\n            3. Incorporate any relevant metadata (e.g., section or document titles) to improve coherence, **but do not assume any domain-specific knowledge** unless explicitly stated.\n            4. Do **not** speculate beyond the visible content.\n\n\n\n            Output Format:\n            Preceding Text Summary:\n            Provide a concise summary of the preceding text that gives context to the image.\n            Image Summary:\n            Provide a summary of the image, describing its purpose and content based on the context.\n            Following Text Summary:\n            Provide a concise summary of the following text that elaborates on the information related to the image.",
    "img_summary": "",
    "embedding_prompt": "",
    "generate_prompt": "This is an image from the file 'Mother_of_Flamlings_Spirit.md', This is the 2th image in the document, "
}