{
    "chunk_id": 451778767831,
    "source_file": "Secrets_in_Black_Myth_Wukong.md",
    "content_type": "one",
    "h1_title": "Chapter 2 Secrets",
    "h2_title": "",
    "content": "Chapter 2 has a lot more secrets to uncover, including another hidden area that opens up after finishing a side quest and some Key Items that will help you reach missable bosses.",
    "promot": "This excerpt is taken from the file \"Secrets_in_Black_Myth_Wukong.md\", under the primary heading \"Chapter 2 Secrets\". The content is presented below:\n\nChapter 2 has a lot more secrets to uncover, including another hidden area that opens up after finishing a side quest and some Key Items that will help you reach missable bosses.",
    "promot_tokens_num": 72
}