{
    "chunk_id": 644906728556,
    "source_file": "Tiger's_Acolyte.md",
    "content_type": "two",
    "h1_title": "Tiger's Acolyte",
    "h2_title": "Where to Find the Tiger's Acolyte",
    "content": "As an optional boss, the Tiger's Acolyte is easily missed as he resides in an entirely optional area in the Yellow Wind Formation, far at the back of the Yellow Wind Ridge in Chapter 2. To reach him, you'll need to head past the Crouching Tiger Temple, and up toward the Windrest Bridge. \n\n\n\nTravel through the Windrest Hamlet area across a second bridge past the Windrest Bridge Shrine, and you can locate this boss in the middle of the final bridge leading back toward the Fright Cliff.",
    "promot": "This excerpt is taken from the file \"Tiger's_Acolyte.md\", within the section \"Tiger's Acolyte\" and the sub-section \"Where to Find the Tiger's Acolyte\". The content is presented below:\n\nAs an optional boss, the Tiger's Acolyte is easily missed as he resides in an entirely optional area in the Yellow Wind Formation, far at the back of the Yellow Wind Ridge in Chapter 2. To reach him, you'll need to head past the Crouching Tiger Temple, and up toward the Windrest Bridge. \n\n\n\nTravel through the Windrest Hamlet area across a second bridge past the Windrest Bridge Shrine, and you can locate this boss in the middle of the final bridge leading back toward the Fright Cliff.",
    "promot_tokens_num": 156
}