{
    "chunk_id": 737709471931,
    "source_file": "Black_Myth_Wukong_Guide.md",
    "content_type": "one",
    "h1_title": "Black Myth: Wukong Guide",
    "h2_title": "",
    "content": "**Released (Platforms)**  \n---  \nAugust 20, 2024 (PC, PS5)  \nTBA (Xbox Series S|X   \n**Developer**| **Publisher**  \nGame Science |  Game Science   \n\nWelcome to IGN's Guide to Black Myth: Wukong, an Action RPG by developer Game Science set in the ancient realm of the classic Chinese tale, Journey to the West. As a Monkey Warrior destined to follow in the footsteps of the legendary Sun Wukong, you'll journey across ancient China and face off against countless fearsome Yaoguai creatures. \n\nTaking place long after the end of Sun Wukong's famous tale, you'll journey to different regions all over China, from serene forests filled with wolf and snake demons, to parched desert ridges and snow mountains and more. Your quest will be to find and collect all six of Sun Wukon's Sage Relics, but you'll need to master the art of the staff and Sun Wukong's famous magical abilities to survive the many Yaoguai Kings that stand in your way.",
    "promot": "This excerpt is taken from the file \"Black_Myth_Wukong_Guide.md\", under the primary heading \"Black Myth: Wukong Guide\". The content is presented below:\n\n**Released (Platforms)**  \n---  \nAugust 20, 2024 (PC, PS5)  \nTBA (Xbox Series S|X   \n**Developer**| **Publisher**  \nGame Science |  Game Science   \n\nWelcome to IGN's Guide to Black Myth: Wukong, an Action RPG by developer Game Science set in the ancient realm of the classic Chinese tale, Journey to the West. As a Monkey Warrior destined to follow in the footsteps of the legendary Sun Wukong, you'll journey across ancient China and face off against countless fearsome Yaoguai creatures. \n\nTaking place long after the end of Sun Wukong's famous tale, you'll journey to different regions all over China, from serene forests filled with wolf and snake demons, to parched desert ridges and snow mountains and more. Your quest will be to find and collect all six of Sun Wukon's Sage Relics, but you'll need to master the art of the staff and Sun Wukong's famous magical abilities to survive the many Yaoguai Kings that stand in your way.",
    "promot_tokens_num": 258
}