{
    "chunk_id": 248794129904,
    "source_file": "The_Spirit_of_Captain_Kalpa-Wave.md",
    "content_type": "one",
    "h1_title": "Where to use The Spirit of Captain Kalpa-Wave in Black Myth: Wukong",
    "h2_title": "",
    "content": "The Spirit of Captain Kalpa-Wave can be used in conjunction with The Spirit of Captain Lotus-Vision, The Spirit of Captain-Wise Voice\"), and The Spirit of Captain Void-Illusion in The New West at the prisoner in the first cell at the base of the Pagoda Realm. With all of these items, you can return to the prisoner to obtain the Chubai Spearhead. \n\n\n\nThis material can be used to craft one of the higher-end Weapons in the game.",
    "promot": "This excerpt is taken from the file \"The_Spirit_of_Captain_Kalpa-Wave.md\", under the primary heading \"Where to use The Spirit of Captain Kalpa-Wave in Black Myth: Wukong\". The content is presented below:\n\nThe Spirit of Captain Kalpa-Wave can be used in conjunction with The Spirit of Captain Lotus-Vision, The Spirit of Captain-Wise Voice\"), and The Spirit of Captain Void-Illusion in The New West at the prisoner in the first cell at the base of the Pagoda Realm. With all of these items, you can return to the prisoner to obtain the Chubai Spearhead. \n\n\n\nThis material can be used to craft one of the higher-end Weapons in the game.",
    "promot_tokens_num": 150
}