{
    "chunk_id": 131957259834,
    "source_file": "Crow_Diviner_Spirit.md",
    "content_type": "paragraph",
    "h1_title": "Crow Diviner Spirit",
    "h2_title": "Crow Diviner Spirit",
    "h3_title": "",
    "content": "The Crow Diviner's Spirit Power allows you to embody him for a short time and cover the surrounding area in a blanket of frost. This frost deals Frost Bane to both you and your enemies. Thankfully, the Crow Diviner's equipped effect makes you more resistant to Frost Bane, so it won't affect you as much as it will your foes.",
    "promot": "This is an excerpt from the file 'Crow_Diviner_Spirit.md', within the main section titled 'Crow Diviner Spirit', specifically from the subsection 'Crow Diviner Spirit'.\nThe content is as follows:\nThe Crow Diviner's Spirit Power allows you to embody him for a short time and cover the surrounding area in a blanket of frost. This frost deals Frost Bane to both you and your enemies. Thankfully, the Crow Diviner's equipped effect makes you more resistant to Frost Bane, so it won't affect you as much as it will your foes.",
    "promot_tokens_num": 115
}