{
    "chunk_id": 45362439032,
    "source_file": "Woods_of_Ember_Walkthrough.md",
    "content_type": "paragraph",
    "h1_title": "Woods of Ember Walkthrough",
    "h2_title": "Ashen Pass I",
    "h3_title": "Boss Fight - Pale-Axe Stalwart",
    "content": "When his dialogue begins to repeat, resume your exploration of the area. First, go over to where there are four chests by the wall (opposite where you first entered the area). Two of the chests are already open, but there are two more to loot. Inside these, you'll find Cold Iron Leaves, Will, a Mind Core, and a Gold Tree Core.",
    "promot": "This is an excerpt from the file 'Woods_of_Ember_Walkthrough.md', within the main section titled 'Woods of Ember Walkthrough', specifically from the subsection 'Ashen Pass I' and the sub-subsection 'Boss Fight - Pale-Axe Stalwart'.\nThe content is as follows:\nWhen his dialogue begins to repeat, resume your exploration of the area. First, go over to where there are four chests by the wall (opposite where you first entered the area). Two of the chests are already open, but there are two more to loot. Inside these, you'll find Cold Iron Leaves, Will, a Mind Core, and a Gold Tree Core.",
    "promot_tokens_num": 138
}