{
    "chunk_id": 454682998895,
    "source_file": "Webbed_Hollow-Middle_Hollow_Walkthrough.md",
    "content_type": "paragraph",
    "h1_title": "Webbed Hollow - Middle Hollow Walkthrough",
    "h2_title": "Yaoguai Chief Miniboss Fight - Centipede Guai",
    "h3_title": "",
    "content": "While it does move fast, it's also extremely susceptible to a well-timed Rock Solid Deflection, and when done at the right time, will topple it to the ground. Use this period to unleash your focus points for a big hit, and it will struggle to rise and give you more time to Immobilize it and keep it vulnerable to more damage.",
    "promot": "This is an excerpt from the file 'Webbed_Hollow-Middle_Hollow_Walkthrough.md', within the main section titled 'Webbed Hollow - Middle Hollow Walkthrough', specifically from the subsection 'Yaoguai Chief Miniboss Fight - Centipede Guai'.\nThe content is as follows:\nWhile it does move fast, it's also extremely susceptible to a well-timed Rock Solid Deflection, and when done at the right time, will topple it to the ground. Use this period to unleash your focus points for a big hit, and it will struggle to rise and give you more time to Immobilize it and keep it vulnerable to more damage.",
    "promot_tokens_num": 136
}