{
    "chunk_id": 206803715177,
    "source_file": "Erlang,_The_Sacred_Divinity.md",
    "content_type": "paragraph",
    "h1_title": "Erlang, The Sacred Divinity",
    "h2_title": "How to Unlock Mount Mei",
    "h3_title": "",
    "content": "There are several steps you need to take to unlock Mount Mei. You can find a detailed breakdown on our dedicated page: How to Unlock the Secret Ending (True Ending) \"How to Unlock the Secret Ending \\(True Ending\\)\"). But here's a quick rundown of everything you'll need to do by Chapter 6 to reach it.",
    "promot": "This is an excerpt from the file 'Erlang,_The_Sacred_Divinity.md', within the main section titled 'Erlang, The Sacred Divinity', specifically from the subsection 'How to Unlock Mount Mei'.\nThe content is as follows:\nThere are several steps you need to take to unlock Mount Mei. You can find a detailed breakdown on our dedicated page: How to Unlock the Secret Ending (True Ending) \"How to Unlock the Secret Ending \\(True Ending\\)\"). But here's a quick rundown of everything you'll need to do by Chapter 6 to reach it.",
    "promot_tokens_num": 120
}