{
    "chunk_id": 888528613936,
    "source_file": "Mother_of_Flamlings_Spirit.md",
    "content_type": "paragraph",
    "h1_title": "Mother of Flamlings Spirit",
    "h2_title": "",
    "h3_title": "",
    "content": "The **Mother of Flamlings** is a foe that you will face off against in Black Myth: Wukong. Once defeated, the Mother of Flamlings offers up her Spirit for you to absorb, allowing you to use some of her powers for a short time. On this page, we will go over everything you need to know about the Mother of Flamlings, including where to find her, how to defeat her, and what power her Spirit gives you.",
    "promot": "This is an excerpt from the file 'Mother_of_Flamlings_Spirit.md', within the main section titled 'Mother of Flamlings Spirit'.\nThe content is as follows:\nThe **Mother of Flamlings** is a foe that you will face off against in Black Myth: Wukong. Once defeated, the Mother of Flamlings offers up her Spirit for you to absorb, allowing you to use some of her powers for a short time. On this page, we will go over everything you need to know about the Mother of Flamlings, including where to find her, how to defeat her, and what power her Spirit gives you.",
    "promot_tokens_num": 133
}