{
    "chunk_id": 517997493462,
    "source_file": "How_to_Find_All_Purple_Talisman_Altars_in_Chapter_4.md",
    "content_type": "paragraph",
    "h1_title": "How to Find All Purple Talisman Altars in Chapter 4",
    "h2_title": "How to Find the Purple Talismans in the Webbed Hollow",
    "h3_title": "",
    "content": "There are 4 Purple Talismans to find. You can pick up 3 of them throughout the Webbed Hollow, and the last one is collected from the Temple of the Yellow Flowers. You'll find a detailed walkthrough below of where to get each one.",
    "promot": "This is an excerpt from the file 'How_to_Find_All_Purple_Talisman_Altars_in_Chapter_4.md', within the main section titled 'How to Find All Purple Talisman Altars in Chapter 4', specifically from the subsection 'How to Find the Purple Talismans in the Webbed Hollow'.\nThe content is as follows:\nThere are 4 Purple Talismans to find. You can pick up 3 of them throughout the Webbed Hollow, and the last one is collected from the Temple of the Yellow Flowers. You'll find a detailed walkthrough below of where to get each one.",
    "promot_tokens_num": 125
}