{
    "chunk_id": 875954970043,
    "source_file": "Black_Loong.md",
    "content_type": "paragraph",
    "h1_title": "Black Loong",
    "h2_title": "Where to Find Black Loong",
    "h3_title": "",
    "content": "With the Loong Scales, you'll be able to interact with the sandfall and remove it as a barrier, revealing a door behind it to take you into the Black Loong's lair.",
    "promot": "This is an excerpt from the file 'Black_Loong.md', within the main section titled 'Black Loong', specifically from the subsection 'Where to Find Black Loong'.\nThe content is as follows:\nWith the Loong Scales, you'll be able to interact with the sandfall and remove it as a barrier, revealing a door behind it to take you into the Black Loong's lair.",
    "promot_tokens_num": 83
}