{
    "chunk_id": 896211754591,
    "source_file": "Coconut_Wine.md",
    "content_type": "paragraph",
    "h1_title": "Coconut Wine",
    "h2_title": "",
    "h3_title": "",
    "content": "You can then use these unique Crafting Materials to upgrade the Drink at the Shen Monkey Vendor in Bamboo Grove within Black Wind Mountain. Each upgrade will provide a sizeable buff to your healing potential, but as you level the Drink up, more Awoken Wine Worms will be needed.",
    "promot": "This is an excerpt from the file 'Coconut_Wine.md', within the main section titled 'Coconut Wine'.\nThe content is as follows:\nYou can then use these unique Crafting Materials to upgrade the Drink at the Shen Monkey Vendor in Bamboo Grove within Black Wind Mountain. Each upgrade will provide a sizeable buff to your healing potential, but as you level the Drink up, more Awoken Wine Worms will be needed.",
    "promot_tokens_num": 86
}