{
    "chunk_id": 549021620950,
    "source_file": "Flame_Ebongold.md",
    "content_type": "paragraph",
    "h1_title": "Flame Ebongold",
    "h2_title": "",
    "h3_title": "",
    "content": "The Flame Ebongold can be used to craft the Wind Bear Staff from the Shrine.",
    "promot": "This is an excerpt from the file 'Flame_Ebongold.md', within the main section titled 'Flame Ebongold'.\nThe content is as follows:\nThe Flame Ebongold can be used to craft the Wind Bear Staff from the Shrine.",
    "promot_tokens_num": 52
}