{
    "chunk_id": 846518039220,
    "source_file": "New_Thunderclap_Temple_Walkthrough.md",
    "content_type": "paragraph",
    "h1_title": "New Thunderclap Temple Walkthrough",
    "h2_title": "Temple Inner Courtyard",
    "h3_title": "Yaoguai Chief Miniboss Fight - Non-Pure",
    "content": "Given his long sweeping swings, having backup from A Pluck of Many or Spirits that summon other allies won't work as well as they'll tend to get hit even if he's focusing all his attention on you.",
    "promot": "This is an excerpt from the file 'New_Thunderclap_Temple_Walkthrough.md', within the main section titled 'New Thunderclap Temple Walkthrough', specifically from the subsection 'Temple Inner Courtyard' and the sub-subsection 'Yaoguai Chief Miniboss Fight - Non-Pure'.\nThe content is as follows:\nGiven his long sweeping swings, having backup from A Pluck of Many or Spirits that summon other allies won't work as well as they'll tend to get hit even if he's focusing all his attention on you.",
    "promot_tokens_num": 113
}