{
    "chunk_id": 686104729122,
    "source_file": "Forest_of_Wolves_Walkthrough.md",
    "content_type": "paragraph",
    "h1_title": "The Forest of Wolves",
    "h2_title": "Front Hills",
    "h3_title": "",
    "content": "Going left should lead you to another Wolf Swordsworn behind a rock sculpture, and a **Gentian** plant near him that you can harvest.",
    "promot": "This is an excerpt from the file 'Forest_of_Wolves_Walkthrough.md', within the main section titled 'The Forest of Wolves', specifically from the subsection 'Front Hills'.\nThe content is as follows:\nGoing left should lead you to another Wolf Swordsworn behind a rock sculpture, and a **Gentian** plant near him that you can harvest.",
    "promot_tokens_num": 73
}