{
    "chunk_id": 801329349375,
    "source_file": "Keeness_of_Tiger.md",
    "content_type": "paragraph",
    "h1_title": "Keeness of Tiger",
    "h2_title": "",
    "h3_title": "",
    "content": "For a full guide through the Crouching Tiger Temple area, be sure to read through our Crouching Tiger Temple Walkthrough in Chapter 2 - Yellow Sand, Desolate Dusk.",
    "promot": "This is an excerpt from the file 'Keeness_of_Tiger.md', within the main section titled 'Keeness of Tiger'.\nThe content is as follows:\nFor a full guide through the Crouching Tiger Temple area, be sure to read through our Crouching Tiger Temple Walkthrough in Chapter 2 - Yellow Sand, Desolate Dusk.",
    "promot_tokens_num": 71
}