{
    "chunk_id": 205644427173,
    "source_file": "Bitter_Lake_Walkthrough.md",
    "content_type": "paragraph",
    "h1_title": "Bitter Lake Walkthrough",
    "h2_title": "Yaoguai Chief Miniboss Fight - Apramana Bat",
    "h3_title": "",
    "content": "At the top of the stone stair path, there's a small side path leading back to a spot with a Ginsengling overlooking the enclosure, and a tunnel. Take the tunnel, and you'll find a shortcut back toward the North Shore Shrine, but first you'll need to deal with a few Monk Supporters holding their heavy stones.",
    "promot": "This is an excerpt from the file 'Bitter_Lake_Walkthrough.md', within the main section titled 'Bitter Lake Walkthrough', specifically from the subsection 'Yaoguai Chief Miniboss Fight - Apramana Bat'.\nThe content is as follows:\nAt the top of the stone stair path, there's a small side path leading back to a spot with a Ginsengling overlooking the enclosure, and a tunnel. Take the tunnel, and you'll find a shortcut back toward the North Shore Shrine, but first you'll need to deal with a few Monk Supporters holding their heavy stones.",
    "promot_tokens_num": 121
}