{
    "chunk_id": 104840826687,
    "source_file": "Best_Skills_to_Unlock.md",
    "content_type": "paragraph",
    "h1_title": "Best Skills to Unlock",
    "h2_title": "How to Understand the Mid-to-Late Game Skills Trees",
    "h3_title": "Best Transformations Skills to Unlock",
    "content": "Skill Name | Description   \n---|---  \n**Moon Roam**|  Damage is increased after a Perfect Dodge   \n**Evergreen**|  Might decay is reduced   \n**Ferocious Form**|  Attack is increased while Transformed",
    "promot": "This is an excerpt from the file 'Best_Skills_to_Unlock.md', within the main section titled 'Best Skills to Unlock', specifically from the subsection 'How to Understand the Mid-to-Late Game Skills Trees' and the sub-subsection 'Best Transformations Skills to Unlock'.\nThe content is as follows:\nSkill Name | Description   \n---|---  \n**Moon Roam**|  Damage is increased after a Perfect Dodge   \n**Evergreen**|  Might decay is reduced   \n**Ferocious Form**|  Attack is increased while Transformed",
    "promot_tokens_num": 112
}