{
    "chunk_id": 756137801405,
    "source_file": "Chapter_4-Rosy_Cheeks,_Gray_Hair.md",
    "content_type": "paragraph",
    "h1_title": "Chapter 4 Walkthrough Sections",
    "h2_title": "",
    "h3_title": "",
    "content": "See the links below to get started with help for a particular section:",
    "promot": "This is an excerpt from the file 'Chapter_4-Rosy_Cheeks,_Gray_Hair.md', within the main section titled 'Chapter 4 Walkthrough Sections'.\nThe content is as follows:\nSee the links below to get started with help for a particular section:",
    "promot_tokens_num": 56
}