{
    "chunk_id": 236146561221,
    "source_file": "Chapter_4_Secret-Purple_Cloud_Mountain_Walkthrough.md",
    "content_type": "paragraph",
    "h1_title": "Chapter 4 Secret - Purple Cloud Mountain Walkthrough",
    "h2_title": "Yaoguai King Boss Fight - The Duskveil",
    "h3_title": "",
    "content": "The Duskveil",
    "promot": "This is an excerpt from the file 'Chapter_4_Secret-Purple_Cloud_Mountain_Walkthrough.md', within the main section titled 'Chapter 4 Secret - Purple Cloud Mountain Walkthrough', specifically from the subsection 'Yaoguai King Boss Fight - The Duskveil'.\nThe content is as follows:\nThe Duskveil",
    "promot_tokens_num": 70
}