{
    "chunk_id": 786655626414,
    "source_file": "Bull_Governor_Spirit.md",
    "content_type": "paragraph",
    "h1_title": "Bull Governor Spirit",
    "h2_title": "",
    "h3_title": "",
    "content": "The **Bull Governor** is a foe that you will face off against in Black Myth: Wukong. Once defeated, the Bull Governor offers up his Spirit for you to absorb, allowing you to use some of his powers for a short time. On this page, we will go over everything you need to know about the Bull Governor, including where to find him, how to defeat him, and what power his Spirit gives you.",
    "promot": "This is an excerpt from the file 'Bull_Governor_Spirit.md', within the main section titled 'Bull Governor Spirit'.\nThe content is as follows:\nThe **Bull Governor** is a foe that you will face off against in Black Myth: Wukong. Once defeated, the Bull Governor offers up his Spirit for you to absorb, allowing you to use some of his powers for a short time. On this page, we will go over everything you need to know about the Bull Governor, including where to find him, how to defeat him, and what power his Spirit gives you.",
    "promot_tokens_num": 122
}