{
    "chunk_id": 763234991548,
    "source_file": "Venom_Daoist.md",
    "content_type": "paragraph",
    "h1_title": "Venom Daoist",
    "h2_title": "Venom Daoist Boss Fight and Guide - Second Encounter",
    "h3_title": "",
    "content": "In your last encounter with the Venom Daoist, he sported quite a bit of arms -- some of which you may have lopped off during the course of the fight. This time, he only has two extra arms, but the same rules still apply for this fight -- at least part of it.",
    "promot": "This is an excerpt from the file 'Venom_Daoist.md', within the main section titled 'Venom Daoist', specifically from the subsection 'Venom Daoist Boss Fight and Guide - Second Encounter'.\nThe content is as follows:\nIn your last encounter with the Venom Daoist, he sported quite a bit of arms -- some of which you may have lopped off during the course of the fight. This time, he only has two extra arms, but the same rules still apply for this fight -- at least part of it.",
    "promot_tokens_num": 110
}