{
    "chunk_id": 612519981860,
    "source_file": "Dark_Thunder.md",
    "content_type": "paragraph",
    "h1_title": "Dark Thunder",
    "h2_title": "",
    "h3_title": "",
    "content": "With the Dark Thunder Transformation, you are able to turn into a horse guai and be immune to Thunder Damage, inflicting Thunder Bane on the enemy with each attack. Any Focus built up before transformation can be converted for use afterward. Dark Thunder's moveset is:",
    "promot": "This is an excerpt from the file 'Dark_Thunder.md', within the main section titled 'Dark Thunder'.\nThe content is as follows:\nWith the Dark Thunder Transformation, you are able to turn into a horse guai and be immune to Thunder Damage, inflicting Thunder Bane on the enemy with each attack. Any Focus built up before transformation can be converted for use afterward. Dark Thunder's moveset is:",
    "promot_tokens_num": 83
}