{
    "chunk_id": 568635880467,
    "source_file": "Webbed_Hollow-Upper_Hollow_Walkthrough.md",
    "content_type": "paragraph",
    "h1_title": "Webbed Hollow - Upper Hollow Walkthrough",
    "h2_title": "Boss Fight - Venom Daoist",
    "h3_title": "",
    "content": "The Venom Daoist usually starts with his most basic attack, holding both swords to his side, and then springing forward with a dual slash on your right. He'll quickly follow up by rolling over to stab at the ground, and then after a moment leap into the air to slam down on top of you.",
    "promot": "This is an excerpt from the file 'Webbed_Hollow-Upper_Hollow_Walkthrough.md', within the main section titled 'Webbed Hollow - Upper Hollow Walkthrough', specifically from the subsection 'Boss Fight - Venom Daoist'.\nThe content is as follows:\nThe Venom Daoist usually starts with his most basic attack, holding both swords to his side, and then springing forward with a dual slash on your right. He'll quickly follow up by rolling over to stab at the ground, and then after a moment leap into the air to slam down on top of you.",
    "promot_tokens_num": 117
}