{
    "chunk_id": 402330536642,
    "source_file": "Webbed_Hollow-Middle_Hollow_Walkthrough.md",
    "content_type": "paragraph",
    "h1_title": "Webbed Hollow - Middle Hollow Walkthrough",
    "h2_title": "Yaoguai Chief Miniboss Fight - Centipede Guai",
    "h3_title": "",
    "content": "However, when you see the Centipede Guai stand up on its two legs, back off your attack immediately. It will start spewing poison down below its body as it staggers around, hoping to catch you unaware.",
    "promot": "This is an excerpt from the file 'Webbed_Hollow-Middle_Hollow_Walkthrough.md', within the main section titled 'Webbed Hollow - Middle Hollow Walkthrough', specifically from the subsection 'Yaoguai Chief Miniboss Fight - Centipede Guai'.\nThe content is as follows:\nHowever, when you see the Centipede Guai stand up on its two legs, back off your attack immediately. It will start spewing poison down below its body as it staggers around, hoping to catch you unaware.",
    "promot_tokens_num": 108
}