{
    "chunk_id": 498692445881,
    "source_file": "Quick_as_Fire,_Fast_as_Wind.md",
    "content_type": "paragraph",
    "h1_title": "Quick as Fire, Fast as Wind",
    "h2_title": "How to Find Quick as Fire, Fast as Wind",
    "h3_title": "",
    "content": "Enter a large open area to find the fox guai suspended from a tree, and her two captors on the way. After she explains that she's been captured, two giant heads will descend upon the arena.",
    "promot": "This is an excerpt from the file 'Quick_as_Fire,_Fast_as_Wind.md', within the main section titled 'Quick as Fire, Fast as Wind', specifically from the subsection 'How to Find Quick as Fire, Fast as Wind'.\nThe content is as follows:\nEnter a large open area to find the fox guai suspended from a tree, and her two captors on the way. After she explains that she's been captured, two giant heads will descend upon the arena.",
    "promot_tokens_num": 98
}