{
    "chunk_id": 84076840762,
    "source_file": "Essential_Tips_and_Tricks.md",
    "img_url": "https://oyster.ignimgs.com/mediawiki/apis.ign.com/black-myth-wukong/5/58/Tips_and_Tricks_%285%29.png",
    "alt_text": "Tips and Tricks \\(5\\).png",
    "position_desc": 2,
    "summary_promot": "\"You are shown an image extracted from a video game walkthrough or strategy guide.\n\n\"\n        \"Your task is to write a short, clear, and informative **English summary** of the image.\n\"\n        \"Do **not** speculate beyond what is explicitly visible in the image.\"",
    "img_summary": "The image shows an in-game menu from a video game, where the player interacts with a character named \"Shen Monkey.\" The menu options include \"Upgrade Gourds,\" \"Upgrade Drinks,\" \"Brew,\" \"Store,\" and \"Leave.\" The currently selected option is \"Upgrade Gourds,\" with a description below stating, \"Upgrade Gourds that have been obtained.\" Shen Monkey, a humanoid monkey character, is seated on a mat surrounded by large jars in a natural, outdoor setting illuminated by warm light."
}