{
    "chunk_id": 156132463382,
    "source_file": "Wind_Bear_Staff.md",
    "img_url": "https://oyster.ignimgs.com/mediawiki/apis.ign.com/black-myth-wukong/8/87/Wind_Bear_Staff_2.jpg",
    "alt_text": "Wind Bear Staff 2.jpg",
    "position_desc": 1,
    "summary_promot": "\"You are shown an image extracted from a video game walkthrough or strategy guide.\n\n\"\n        \"Your task is to write a short, clear, and informative **English summary** of the image.\n\"\n        \"Do **not** speculate beyond what is explicitly visible in the image.\"",
    "img_summary": "The image displays a video game interface showing the equipment screen for a character wielding a \"Wind Bear Staff,\" classified as a rare item. The staff has an attack value of 50 and a critical hit chance of 4%. It possesses a unique effect that significantly boosts the critical hit chance of the \"Unveiling Strike of Cloud Step.\" The character is wearing a detailed mask and armor, holding the staff prominently. The screen includes various character stats such as health, stamina, and other attributes, with a total score of 25. A quote at the bottom reads, \"Where'er it goes, or steps may lead, Beasts quake in fear, and evils recede.\""
}