{
    "chunk_id": 571769371289,
    "source_file": "Silk.md",
    "img_url": "https://oyster.ignimgs.com/mediawiki/apis.ign.com/black-myth-wukong/2/2d/Silk.jpg",
    "alt_text": "Silk.jpg",
    "position_desc": 1,
    "summary_promot": "\"You are shown an image extracted from a video game walkthrough or strategy guide.\n\n\"\n        \"Your task is to write a short, clear, and informative **English summary** of the image.\n\"\n        \"Do **not** speculate beyond what is explicitly visible in the image.\"",
    "img_summary": "The image shows a screenshot from a video game inventory menu. The selected item is \"Silk,\" categorized as a rare general armor material. The description indicates that the silk is produced by an old silkworm and can be used to craft armor. The player currently holds 2 out of a possible 999 units of silk. The inventory displays various materials, each with a quantity, and the player has a total of 2117 currency or points. Options at the bottom of the screen allow the player to examine, sort, or return from the inventory menu."
}