{
    "chunk_id": 173605329201,
    "source_file": "Emerald-Armed_Mantis.md",
    "img_url": "https://oyster.ignimgs.com/mediawiki/apis.ign.com/black-myth-wukong/a/ae/Foothills_Walkthrough_%2879%29.png",
    "alt_text": "Foothills Walkthrough \\(79\\).png",
    "position_desc": 3,
    "summary_promot": "\"You are shown an image extracted from a video game walkthrough or strategy guide.\n\n\"\n        \"Your task is to write a short, clear, and informative **English summary** of the image.\n\"\n        \"Do **not** speculate beyond what is explicitly visible in the image.\"",
    "img_summary": "The image depicts a large, insect-like creature standing in a dark environment. The creature has a humanoid form with green exoskeleton, large wings, and claw-like appendages raised above its head. It appears to be confronting a smaller, armored figure wielding a spear. The scene is atmospheric, with red particles scattered throughout the background, suggesting a tense or hostile encounter."
}