{
    "chunk_id": 373970008511,
    "source_file": "Weapons.md",
    "img_url": "https://oyster.ignimgs.com/mediawiki/apis.ign.com/black-myth-wukong/d/d3/Willow_Wood_Staff_.jpg",
    "alt_text": "Willow Wood Staff .jpg",
    "position_desc": 1,
    "summary_promot": "\"You are shown an image extracted from a video game walkthrough or strategy guide.\n\n\"\n        \"Your task is to write a short, clear, and informative **English summary** of the image.\n\"\n        \"Do **not** speculate beyond what is explicitly visible in the image.\"",
    "img_summary": "The image shows a person holding a staff-like weapon. The staff is intricately designed, featuring a rough texture with a series of gold or brass rings around the grip area. The person holding the staff is wearing dark clothing with fur accents, and the background is dimly lit, emphasizing the staff as the focal point of the image."
}