{
    "chunk_id": 555579103997,
    "source_file": "Valley_of_Ecstasy_Walkthrough.md",
    "img_url": "https://oyster.ignimgs.com/mediawiki/apis.ign.com/black-myth-wukong/5/56/Wukong_Karma_20.jpg",
    "alt_text": "Wukong Karma 20.jpg",
    "position_desc": 94,
    "summary_promot": "\"You are shown an image extracted from a video game walkthrough or strategy guide.\n\n\"\n        \"Your task is to write a short, clear, and informative **English summary** of the image.\n\"\n        \"Do **not** speculate beyond what is explicitly visible in the image.\"",
    "img_summary": "The image depicts a scene from a video game set in a snowy landscape. A player-controlled character, wearing red clothing and wielding a staff, is approaching a large creature with horns, dressed in a yellow belt, standing near a wooden structure resembling a torii gate. The game interface displays various icons and bars indicating player abilities and status, such as health and stamina, in the bottom corners of the screen. The environment features rocky terrain and snow-covered ground, suggesting a mountainous or forested area."
}