{
    "chunk_id": 67965703381,
    "source_file": "How_to_Unlock_the_Secret_Loong_Dragon_Bosses.md",
    "img_url": "https://oyster.ignimgs.com/mediawiki/apis.ign.com/black-myth-wukong/b/be/Secret_Loong_Bosses_%2812%29.png",
    "alt_text": "Secret Loong Bosses \\(12\\).png",
    "position_desc": 3,
    "summary_promot": "\"You are shown an image extracted from a video game walkthrough or strategy guide.\n\n\"\n        \"Your task is to write a short, clear, and informative **English summary** of the image.\n\"\n        \"Do **not** speculate beyond what is explicitly visible in the image.\"",
    "img_summary": "The image depicts a scene from a video game where a character is engaged in combat with a large creature amidst a dusty environment. The character is wielding a staff and appears to be running towards the creature, which is partially obscured by a cloud of dust. The creature has visible tentacles. The interface shows various icons and a health bar at the bottom of the screen, indicating gameplay elements such as abilities or items. The text \"First Prince of Flowing Sands\" is displayed, suggesting the name of the creature or the current mission."
}