{
    "chunk_id": 556533389746,
    "source_file": "Old_Rattle-Drum.md",
    "img_url": "https://oyster.ignimgs.com/mediawiki/apis.ign.com/black-myth-wukong/0/0a/Old_Rattle-Drum_1.jpg",
    "alt_text": "Old Rattle-Drum 1.jpg",
    "position_desc": 2,
    "summary_promot": "\"You are shown an image extracted from a video game walkthrough or strategy guide.\n\n\"\n        \"Your task is to write a short, clear, and informative **English summary** of the image.\n\"\n        \"Do **not** speculate beyond what is explicitly visible in the image.\"",
    "img_summary": "The image depicts a scene from a video game where the player character is facing an enemy in a rocky, desert-like environment. The player character is holding a staff and is positioned in the foreground, while the enemy, resembling a large shield with spikes and a glowing center, is in the middle distance. The enemy has a health bar above it, indicating it is a target for combat. In the background, there are stone structures and ruins. The game's interface displays various icons and meters, likely representing health, stamina, and abilities, on the bottom left and right corners of the screen."
}