{
    "chunk_id": 527197296155,
    "source_file": "Erlang,_The_Sacred_Divinity.md",
    "content_type": "paragraph",
    "h1_title": "Erlang, The Sacred Divinity",
    "h2_title": "Erlang, The Sacred Divinity Boss Fight and Guide",
    "h3_title": "",
    "content": "On top of this, you'll start to see him dragging the long sword toward you quickly. Again, this requires fast dodging to avoid it colliding with you. The third time he does this, he will start to shoot lasers, and you'll need to dodge around 4 times to completely miss the attack.",
    "promot": "This is an excerpt from the file 'Erlang,_The_Sacred_Divinity.md', within the main section titled 'Erlang, The Sacred Divinity', specifically from the subsection 'Erlang, The Sacred Divinity Boss Fight and Guide'.\nThe content is as follows:\nOn top of this, you'll start to see him dragging the long sword toward you quickly. Again, this requires fast dodging to avoid it colliding with you. The third time he does this, he will start to shoot lasers, and you'll need to dodge around 4 times to completely miss the attack.",
    "promot_tokens_num": 124
}