{
    "chunk_id": 280347354380,
    "source_file": "Webbed_Hollow-Lower_Hollow_Walkthrough.md",
    "content_type": "paragraph",
    "h1_title": "Webbed Hollow - Lower Hollow Walkthrough",
    "h2_title": "Boss Fight - Zhu Bajie",
    "h3_title": "",
    "content": "There actually isn't anything more you can do in the Hut of Immortality, as all the doors are sealed. However, when you return to the Shrine outside, you'll find a new cave path has been carved out that leads outside to a large muddy hole.",
    "promot": "This is an excerpt from the file 'Webbed_Hollow-Lower_Hollow_Walkthrough.md', within the main section titled 'Webbed Hollow - Lower Hollow Walkthrough', specifically from the subsection 'Boss Fight - Zhu Bajie'.\nThe content is as follows:\nThere actually isn't anything more you can do in the Hut of Immortality, as all the doors are sealed. However, when you return to the Shrine outside, you'll find a new cave path has been carved out that leads outside to a large muddy hole.",
    "promot_tokens_num": 108
}