{
    "chunk_id": 298281600148,
    "source_file": "Rat_Sage_Staff.md",
    "content_type": "paragraph",
    "h1_title": "Rat Sage Staff",
    "h2_title": "",
    "h3_title": "",
    "content": "The Rat Sage Staff Staff is an Epic weapon in Black Myth: Wukong. It comes with solid stats, damage, and a decent, albeit easily outbeaten unique effect compared to the other Weapons in the game.",
    "promot": "This is an excerpt from the file 'Rat_Sage_Staff.md', within the main section titled 'Rat Sage Staff'.\nThe content is as follows:\nThe Rat Sage Staff Staff is an Epic weapon in Black Myth: Wukong. It comes with solid stats, damage, and a decent, albeit easily outbeaten unique effect compared to the other Weapons in the game.",
    "promot_tokens_num": 78
}