{
    "chunk_id": 755920656828,
    "source_file": "Forest_of_Wolves_Walkthrough.md",
    "content_type": "paragraph",
    "h1_title": "The Forest of Wolves",
    "h2_title": "Black Wind Mountain’s Secret - Ringing the First Bell",
    "h3_title": "",
    "content": "With Guangzhi defeated, you can look where he was meditating to find a large bell. Interact with the pole to ring the bell. The Keeper will fret over this, but in reality this is the first of three bells you should seek out in Chapter 1 to uncover a major secret!",
    "promot": "This is an excerpt from the file 'Forest_of_Wolves_Walkthrough.md', within the main section titled 'The Forest of Wolves', specifically from the subsection 'Black Wind Mountain’s Secret - Ringing the First Bell'.\nThe content is as follows:\nWith Guangzhi defeated, you can look where he was meditating to find a large bell. Interact with the pole to ring the bell. The Keeper will fret over this, but in reality this is the first of three bells you should seek out in Chapter 1 to uncover a major secret!",
    "promot_tokens_num": 112
}