{
    "chunk_id": 85970965250,
    "source_file": "Webbed_Hollow-Lower_Hollow_Walkthrough.md",
    "content_type": "paragraph",
    "h1_title": "Webbed Hollow - Lower Hollow Walkthrough",
    "h2_title": "Relief of the Fallen Loong",
    "h3_title": "",
    "content": "Off on the right side, there's a larger tree where you can find a **Luojia Fragrant Vine** above a pool of water, and then find a path leading up to the left.",
    "promot": "This is an excerpt from the file 'Webbed_Hollow-Lower_Hollow_Walkthrough.md', within the main section titled 'Webbed Hollow - Lower Hollow Walkthrough', specifically from the subsection 'Relief of the Fallen Loong'.\nThe content is as follows:\nOff on the right side, there's a larger tree where you can find a **Luojia Fragrant Vine** above a pool of water, and then find a path leading up to the left.",
    "promot_tokens_num": 96
}