{
    "chunk_id": 732104129038,
    "source_file": "Kang-Jin_Star.md",
    "content_type": "paragraph",
    "h1_title": "Kang-Jin Star",
    "h2_title": "Where to Find Kang-Jin Star",
    "h3_title": "Kang-Jin Star Boss Fight and Guide",
    "content": "When appearing to float up above you, watch carefully if she summons an electrical imbued spike in her hand. She'll fly down close to throw it at the ground, and even if you dodge you'll need to watch for when it creates a tremor to explode the ground around it.",
    "promot": "This is an excerpt from the file 'Kang-Jin_Star.md', within the main section titled 'Kang-Jin Star', specifically from the subsection 'Where to Find Kang-Jin Star' and the sub-subsection 'Kang-Jin Star Boss Fight and Guide'.\nThe content is as follows:\nWhen appearing to float up above you, watch carefully if she summons an electrical imbued spike in her hand. She'll fly down close to throw it at the ground, and even if you dodge you'll need to watch for when it creates a tremor to explode the ground around it.",
    "promot_tokens_num": 121
}