{
    "chunk_id": 761177766017,
    "source_file": "Macaque_Chief.md",
    "content_type": "paragraph",
    "h1_title": "Macaque Chief",
    "h2_title": "Where to Find the Macaque Chief",
    "h3_title": "",
    "content": "The first time you'll encounter this enemy is early in the Snowhill Path as you reach a plateau along the Snowclad Path after you spot the monkey awakening the Frozen Corpses.",
    "promot": "This is an excerpt from the file 'Macaque_Chief.md', within the main section titled 'Macaque Chief', specifically from the subsection 'Where to Find the Macaque Chief'.\nThe content is as follows:\nThe first time you'll encounter this enemy is early in the Snowhill Path as you reach a plateau along the Snowclad Path after you spot the monkey awakening the Frozen Corpses.",
    "promot_tokens_num": 82
}