{
    "chunk_id": 517934618784,
    "source_file": "Yellowbrow.md",
    "content_type": "paragraph",
    "h1_title": "Yellowbrow",
    "h2_title": "Yellowbrow Boss Fight (Second Encounter)",
    "h3_title": "",
    "content": "In this form, your attacks will simply bounce off like the Tiger Vanguard's Stone Form, but he won't readily revert back, and continue to attack in this impervious form.",
    "promot": "This is an excerpt from the file 'Yellowbrow.md', within the main section titled 'Yellowbrow', specifically from the subsection 'Yellowbrow Boss Fight (Second Encounter)'.\nThe content is as follows:\nIn this form, your attacks will simply bounce off like the Tiger Vanguard's Stone Form, but he won't readily revert back, and continue to attack in this impervious form.",
    "promot_tokens_num": 81
}