{
    "chunk_id": 624946192689,
    "source_file": "Secret_Bosses_in_Black_Myth_Wukong.md",
    "content_type": "paragraph",
    "h1_title": "Secret Bosses in Chapter 6",
    "h2_title": "Erlang, the Sacred Divinity",
    "h3_title": "",
    "content": "However, there is a final spot that can be unlocked if you meet the right conditions. You'll need to finish the secret areas from each chapter by beating the final bosses in each one and finish the questline for the Green-Capped Martialist from Chapter 3.",
    "promot": "This is an excerpt from the file 'Secret_Bosses_in_Black_Myth_Wukong.md', within the main section titled 'Secret Bosses in Chapter 6', specifically from the subsection 'Erlang, the Sacred Divinity'.\nThe content is as follows:\nHowever, there is a final spot that can be unlocked if you meet the right conditions. You'll need to finish the secret areas from each chapter by beating the final bosses in each one and finish the questline for the Green-Capped Martialist from Chapter 3.",
    "promot_tokens_num": 110
}